enrichme.py
pandas_util.py
enrichme-0.1.1.dist-info/top_level.txt
enrichme-0.1.1.dist-info/METADATA
enrichme-0.1.1.dist-info/entry_points.txt
enrichme-0.1.1.dist-info/DESCRIPTION.rst
enrichme-0.1.1.dist-info/metadata.json
enrichme-0.1.1.dist-info/WHEEL
enrichme-0.1.1.dist-info/RECORD
