Metadata-Version: 2.0
Name: enrichme
Version: 0.1.1
Summary: Test enrichment of genome-wide statistics in gene (or other) categories while correcting for gene-length and clustering.
Home-page: https://github.com/feilchenfeldt/enrichme
Author: Hannes Svardal
Author-email: hannes.svardal@gmail.com
License: MIT
Keywords: Enrichment
Platform: UNKNOWN
Classifier: Development Status :: 5 - Production/Stable
Classifier: Intended Audience :: Developers
Classifier: Topic :: Scientific/Engineering :: Bio-Informatics
Classifier: License :: OSI Approved :: MIT License
Classifier: Programming Language :: Python :: 2
Classifier: Programming Language :: Python :: 2.6
Classifier: Programming Language :: Python :: 2.7
Classifier: Programming Language :: Python :: 3
Classifier: Programming Language :: Python :: 3.2
Classifier: Programming Language :: Python :: 3.3
Classifier: Programming Language :: Python :: 3.4
Requires-Dist: pandas
